LICENSE
MANIFEST.in
README.rst
dev-requirements.txt
requirements.txt
setup.cfg
setup.py
test-requirements.txt
tests.py
sprockets/__init__.py
sprockets.clients.memcached.egg-info/PKG-INFO
sprockets.clients.memcached.egg-info/SOURCES.txt
sprockets.clients.memcached.egg-info/dependency_links.txt
sprockets.clients.memcached.egg-info/namespace_packages.txt
sprockets.clients.memcached.egg-info/not-zip-safe
sprockets.clients.memcached.egg-info/requires.txt
sprockets.clients.memcached.egg-info/top_level.txt
sprockets/clients/__init__.py
sprockets/clients/memcached/__init__.py