Metadata-Version: 1.1
Name: sprockets.clients.memcached
Version: 1.1.0
Summary: Memcached client wrapper that is configured via environment variables
Home-page: https://github.com/sprockets/sprockets.clients.memcached.git
Author: AWeber Communications
Author-email: api@aweber.com
License: Copyright (c) 2014-2018 AWeber Communications
